{"hash":"57e6961ace5b9c74166ad69ef2c153b2e1b0899e","data":{"page":{"id":"bfcea28ece666a004d9a09e3abbc1333","title":"Installation","path":"/p/installation/","parent":"getting-started","beta":null,"content":"<h1 id=\"installation\"><a href=\"#installation\" aria-hidden=\"true\"><span class=\"autolink fa-solid fa-link\"></span></a>Installation</h1>\n<p>Installing the <strong>Grid Engine</strong> plugin is simple.</p>\n<h2 id=\"npm\"><a href=\"#npm\" aria-hidden=\"true\"><span class=\"autolink fa-solid fa-link\"></span></a>NPM</h2>\n<pre class=\"language-bash\"><code class=\"language-bash\"><span class=\"token function\">npm</span> i <span class=\"token parameter variable\">--save</span> grid-engine</code></pre>\n<h2 id=\"web\"><a href=\"#web\" aria-hidden=\"true\"><span class=\"autolink fa-solid fa-link\"></span></a>Web</h2>\n<pre class=\"language-html\"><code class=\"language-html\"><span class=\"token comment\">&lt;!-- Download the .zip and copy GridEngine.min.js from dist/ --></span>\n<span class=\"token tag\"><span class=\"token tag\"><span class=\"token punctuation\">&lt;</span>script</span> <span class=\"token attr-name\">src</span><span class=\"token attr-value\"><span class=\"token punctuation attr-equals\">=</span><span class=\"token punctuation\">\"</span>GridEngine.min.js<span class=\"token punctuation\">\"</span></span><span class=\"token punctuation\">></span></span><span class=\"token script\"></span><span class=\"token tag\"><span class=\"token tag\"><span class=\"token punctuation\">&lt;/</span>script</span><span class=\"token punctuation\">></span></span></code></pre>\n<p>Then, inside your Phaser game config...</p>\n<pre class=\"language-javascript\"><code class=\"language-javascript\"><span class=\"token keyword\">const</span> gameConfig <span class=\"token operator\">=</span> <span class=\"token punctuation\">{</span>\n  <span class=\"token comment\">// ...</span>\n\n  <span class=\"token literal-property property\">plugins</span><span class=\"token operator\">:</span> <span class=\"token punctuation\">{</span>\n    <span class=\"token literal-property property\">scene</span><span class=\"token operator\">:</span> <span class=\"token punctuation\">[</span>\n      <span class=\"token punctuation\">{</span>\n        <span class=\"token literal-property property\">key</span><span class=\"token operator\">:</span> <span class=\"token string\">\"gridEngine\"</span><span class=\"token punctuation\">,</span>\n        <span class=\"token literal-property property\">plugin</span><span class=\"token operator\">:</span> <span class=\"token maybe-class-name\">GridEngine</span><span class=\"token punctuation\">,</span>\n        <span class=\"token literal-property property\">mapping</span><span class=\"token operator\">:</span> <span class=\"token string\">\"gridEngine\"</span><span class=\"token punctuation\">,</span>\n      <span class=\"token punctuation\">}</span><span class=\"token punctuation\">,</span>\n    <span class=\"token punctuation\">]</span><span class=\"token punctuation\">,</span>\n  <span class=\"token punctuation\">}</span><span class=\"token punctuation\">,</span>\n\n  <span class=\"token comment\">// ...</span>\n<span class=\"token punctuation\">}</span><span class=\"token punctuation\">;</span>\n\n<span class=\"token keyword\">const</span> game <span class=\"token operator\">=</span> <span class=\"token keyword\">new</span> <span class=\"token class-name\">Phaser<span class=\"token punctuation\">.</span>Game</span><span class=\"token punctuation\">(</span>gameConfig<span class=\"token punctuation\">)</span><span class=\"token punctuation\">;</span></code></pre>\n<p>Now you're all set to start using <strong>Grid Engine</strong> in your scenes!</p>\n<pre class=\"language-javascript\"><code class=\"language-javascript\"><span class=\"token keyword\">function</span> <span class=\"token function\">create</span><span class=\"token punctuation\">(</span><span class=\"token punctuation\">)</span> <span class=\"token punctuation\">{</span>\n  <span class=\"token comment\">// ...</span>\n\n  <span class=\"token keyword\">const</span> gridEngineConfig <span class=\"token operator\">=</span> <span class=\"token punctuation\">{</span>\n    <span class=\"token literal-property property\">characters</span><span class=\"token operator\">:</span> <span class=\"token punctuation\">[</span>\n      <span class=\"token punctuation\">{</span>\n        <span class=\"token literal-property property\">id</span><span class=\"token operator\">:</span> <span class=\"token string\">\"player\"</span><span class=\"token punctuation\">,</span>\n        <span class=\"token literal-property property\">sprite</span><span class=\"token operator\">:</span> playerSprite<span class=\"token punctuation\">,</span>\n        <span class=\"token literal-property property\">walkingAnimationMapping</span><span class=\"token operator\">:</span> <span class=\"token number\">6</span><span class=\"token punctuation\">,</span>\n      <span class=\"token punctuation\">}</span><span class=\"token punctuation\">,</span>\n    <span class=\"token punctuation\">]</span><span class=\"token punctuation\">,</span>\n  <span class=\"token punctuation\">}</span><span class=\"token punctuation\">;</span>\n\n  <span class=\"token keyword\">this</span><span class=\"token punctuation\">.</span><span class=\"token property-access\">gridEngine</span><span class=\"token punctuation\">.</span><span class=\"token method function property-access\">create</span><span class=\"token punctuation\">(</span>tilemap<span class=\"token punctuation\">,</span> gridEngineConfig<span class=\"token punctuation\">)</span><span class=\"token punctuation\">;</span>\n\n  <span class=\"token comment\">// ...</span>\n<span class=\"token punctuation\">}</span></code></pre>\n"}},"context":{}}